redis_sacsc/__init__.py
redis_sacsc/cache.py
redis_sacsc/client.py
redis_sacsc/connection.py
redis_sacsc/crc.py
redis_sacsc/pubssub_thread.py
redis_sacsc/redis_manager.py
redis_sacsc-0.0.1.dist-info/LICENSE
redis_sacsc-0.0.1.dist-info/WHEEL
redis_sacsc-0.0.1.dist-info/METADATA
redis_sacsc-0.0.1.dist-info/RECORD
