Metadata-Version: 2.1
Name: redis-sacsc
Version: 0.0.1
Summary: Redis Server-Assisted Client-Side Caching in Python
Home-page: https://github.com/iamajay/redis-sacsc
License: MIT
Requires-Python: >=3.6,<4.0
Classifier: Development Status :: 3 - Alpha
Classifier: Intended Audience :: Developers
Classifier: License :: OSI Approved :: MIT License
Classifier: Operating System :: OS Independent
Classifier: Programming Language :: Python :: 3
Classifier: Programming Language :: Python :: 3.6
Classifier: Programming Language :: Python :: 3.7
Classifier: Programming Language :: Python :: 3.8
Classifier: Topic :: Software Development :: Libraries :: Python Modules
Requires-Dist: redis (>=3.4.1,<4.0.0)
Project-URL: Repository, https://github.com/iamajay/redis-sacsc
